{
  "question_id": "72234",
  "level": 2,
  "type": "ppt",
  "content": [
    {
      "type": "text",
      "content": "在某动物保护组织就职的张宇要制作一份介绍世界动物日的PowerPoint演示文稿。按照下列要求，完成演示文稿的制作。\n\n1. 打开考生文件夹下的素材文档PPT.pptx(\".pptx\"为扩展名），后续操作均基于此文件，否则不得分。\n\n2. 将幻灯片大小设置为\"全屏显示（16:9）\"，然后按照如下要求修改幻灯片母版：\n\n①将幻灯片母版名称修改为\"世界动物日\"；母版标题应用\"填充-白色，轮廓-着色1, 阴影\"的艺术字样式，字体为\"微软雅黑\"，并应用加粗效果；母版各级文本样式设置为\"方正姚体\"，文字颜色为\"蓝色，个性色1\"。\n\n②使用\"图片1.png\"作为标题幻灯片版式的背景。\n\n③新建名为\"世界动物日1\"的自定义版式，在该版式中插入\"图片2.png\"，并对齐幻灯片左侧边缘；调整标题占位符的宽度为17.6厘米，将其置于图片右侧；在标题占位符下方插入内容占位符，宽度为17.6厘米，高度为9厘米，并与标题占位符左对齐。\n\n④依据\"世界动物日1\"版式创建名为\"世界动物日2\"的新版式，在\"世界动物日2\"版式中将内容占位符的宽度调整为10厘米（保持与标题占位符左对齐）；在内容占位符右侧插入宽度为7.2厘米、高度为9厘米的图片占位符，并与左侧的内容占位符顶端对齐，与上方的标题占位符右对齐。\n\n3. 演示文稿共包含7张幻灯片，所涉及的文字内容保存在\"文字素材.docx\"文档中，具体所对应的幻灯片可参见\"完成效果.docx\"文档所示样例。其中第1张幻灯片的版式为\"标题幻灯片\"，第2张幻灯片、第4～7张幻灯片的版式为\"世界动物日1\"，第3张幻灯片的版式为\"世界动物日2\"；所有幻灯片中的文字字体保持与母版中的设置一致。\n\n4. 将第2张幻灯片中的项目符号列表转换为SmartArt图形，布局为\"垂直曲形列表\"，图形中的字体为\"方正姚体\"；为SmartArt图形中包含文字内容的5个形状分别建立超链接，链接到后面对应内容的幻灯片。\n\n5. 在第3张幻灯片右侧的图片占位符中插入图片\"图片3.jpg\"，并重设图片及其大小，适当调整其位置；对左侧的文字内容和右侧的图片添加\"淡出\"进入动画效果，并设置在放映时左侧文字内容首先自动出现，在该动画播放完毕且延迟1秒钟后，右侧图片再自动出现。\n\n6. 将第4张幻灯片中的文字转换为8行2列的表格，适当调整表格的行高、列宽以及表格样式；设置文字字体为\"方正姚体\"，字体颜色为\"白色，背景1\"；并应用图片\"表格背景.jpg\"作为表格的背景。\n\n7. 在第7张幻灯片的内容占位符中插入视频\"动物相册.wmv\"，并使用图片\"图片1.png\"作为视频剪辑的预览图像。\n\n8. 在第1张幻灯片中插入\"背景音乐.mid\"文件作为第1～6张幻灯片的背景音乐（即第6张幻灯片放映结束后背景音乐停止），音乐自动播放，且放映时隐藏图标。\n\n9. 为演示文稿中的所有幻灯片应用一种恰当的切换效果，并设置第1～6张幻灯片的自动换片时间为10秒钟，第7张幻灯片的自动换片时间为50秒。\n\n10. 为演示文稿插入幻灯片编号，编号从1开始，标题幻灯片中不显示编号。\n\n11. 将演示文稿中的所有文本\"法兰西斯\"替换为\"方济各\"，并在第1张幻灯片中添加批注，内容为\"圣方济各又称圣法兰西斯。\"\n\n12. 删除\"标题幻灯片\"、\"世界动物日1\"和\"世界动物日2\"之外的其他幻灯片版式。"
    }
  ]
}